<?xml version="1.0"?>
<game_state>
	<file_system />
	<input />
	<window />
	<textures />
	<audio />
	<map />
	<pathfinding />
	<fonts />
	<gui />
	<SceneManager />
	<:anonymous />
	<:anonymous />
	<:anonymous />
	<:anonymous />
	<player>
		<keys id="0" completed="true" />
		<keys id="1" completed="true" />
		<keys id="2" completed="false" />
		<keys id="3" completed="false" />
		<keys id="4" completed="false" />
		<n_keys n="2" />
		<hp curr="4" max="4" />
		<weapons curr_weapon="27" />
		<rupees n="26" />
		<stats power="30" speed="2.5" />
		<items pegasus_boots="true" />
	</player>
	<:anonymous />
	<dialogue />
	<video />
	<renderer>
		<camera x="-1024" y="-1056" />
	</renderer>
</game_state>
